neugym/__init__.py
neugym/exception.py
neugym/environment/__init__.py
neugym/environment/_agent.py
neugym/environment/_object.py
neugym/environment/delayed_reward_gridworld.py
neugym/environment/gridworld.py
neugym/environment/time_limited_gridworld.py
neugym/tests/__init__.py
neugym/tests/test_gridworld.py
neugym/utils/__init__.py
neugym/utils/function.py
neugym-0.1.4.dist-info/LICENSE
neugym-0.1.4.dist-info/METADATA
neugym-0.1.4.dist-info/WHEEL
neugym-0.1.4.dist-info/top_level.txt
neugym-0.1.4.dist-info/RECORD
