Metadata-Version: 2.1
Name: neugym
Version: 0.1.4
Summary: Python package for reinforcement learning environment of animal behavior modeling.
Author: Hao Zhu
Author-email: hao.zhu.10015@gmail.com
License: UNKNOWN
Project-URL: Bug Tracker, https://github.com/HaoZhu10015/neugym/issues
Project-URL: Documentation, https://neugym.readthedocs.io/en/latest/
Project-URL: Source Code, https://github.com/HaoZhu10015/neugym
Platform: UNKNOWN
License-File: LICENSE
Requires-Dist: networkx (>=2.8.5)
Requires-Dist: numpy (>=1.23.0)
Requires-Dist: setuptools (>=61.2.0)
Requires-Dist: pytest (>=7.1.2)
